dominion/__init__.py
dominion/__main__.py
dominion/dominion.py
dominion/dominion_version.py
dominion/data/cards.json
dominion-0.0.1.dist-info/LICENSE
dominion-0.0.1.dist-info/METADATA
dominion-0.0.1.dist-info/WHEEL
dominion-0.0.1.dist-info/entry_points.txt
dominion-0.0.1.dist-info/top_level.txt
dominion-0.0.1.dist-info/RECORD
