Metadata-Version: 2.1
Name: dominion
Version: 0.0.1
Summary: Generate kingdom sets for the card game Dominion
Home-page: https://github.com/dfm/dominion
Author: Dan Foreman-Mackey
Author-email: foreman.mackey@gmail.com
License: MIT
Platform: UNKNOWN
Classifier: Development Status :: 4 - Beta
Classifier: Environment :: Console
Classifier: License :: OSI Approved :: MIT License
Classifier: Operating System :: OS Independent
Classifier: Programming Language :: Python
Classifier: Programming Language :: Python :: 3 :: Only
Requires-Python: >=3.6
Requires-Dist: click
